{
  "entries": {
    "0x8def9f50456c6c4e37fa5d3d57f108ed23992dae": {
      "address": "0x8def9f50456c6c4e37fa5d3d57f108ed23992dae",
      "first_seen_in_top_ms": 1779007621198,
      "runs_in_top": 28,
      "consecutive_in_top": 0,
      "last_rank": 9,
      "last_seen_ms": 1783198415220,
      "new_entrant_announced": true,
      "drop_off_announced": true
    },
    "0x7fdafde5cfb5465924316eced2d3715494c517d1": {
      "address": "0x7fdafde5cfb5465924316eced2d3715494c517d1",
      "first_seen_in_top_ms": 1779007621198,
      "runs_in_top": 279,
      "consecutive_in_top": 10,
      "last_rank": 7,
      "last_seen_ms": 1783632061308,
      "new_entrant_announced": true,
      "drop_off_announced": false
    },
    "0xd47587702a91731dc1089b5db0932cf820151a91": {
      "address": "0xd47587702a91731dc1089b5db0932cf820151a91",
      "first_seen_in_top_ms": 1779007621198,
      "runs_in_top": 147,
      "consecutive_in_top": 0,
      "last_rank": 17,
      "last_seen_ms": 1783198415220,
      "new_entrant_announced": true,
      "drop_off_announced": true
    },
    "0xa65ce1d604fa901c13aa29f2126a57d9032e412b": {
      "address": "0xa65ce1d604fa901c13aa29f2126a57d9032e412b",
      "first_seen_in_top_ms": 1779007621198,
      "runs_in_top": 201,
      "consecutive_in_top": 41,
      "last_rank": 24,
      "last_seen_ms": 1783632061308,
      "new_entrant_announced": true,
      "drop_off_announced": false
    },
    "0xf28e1b06e00e8774c612e31ab3ac35d5a720085f": {
      "address": "0xf28e1b06e00e8774c612e31ab3ac35d5a720085f",
      "first_seen_in_top_ms": 1779007621198,
      "runs_in_top": 121,
      "consecutive_in_top": 0,
      "last_rank": 42,
      "last_seen_ms": 1782423606061,
      "new_entrant_announced": true,
      "drop_off_announced": true
    },
    "0xecb63caa47c7c4e77f60f1ce858cf28dc2b82b00": {
      "address": "0xecb63caa47c7c4e77f60f1ce858cf28dc2b82b00",
      "first_seen_in_top_ms": 1779007621198,
      "runs_in_top": 266,
      "consecutive_in_top": 0,
      "last_rank": 47,
      "last_seen_ms": 1783564860320,
      "new_entrant_announced": true,
      "drop_off_announced": true
    },
    "0xa312114b5795dff9b8db50474dd57701aa78ad1e": {
      "address": "0xa312114b5795dff9b8db50474dd57701aa78ad1e",
      "first_seen_in_top_ms": 1779007621198,
      "runs_in_top": 154,
      "consecutive_in_top": 13,
      "last_rank": 16,
      "last_seen_ms": 1783632061308,
      "new_entrant_announced": true,
      "drop_off_announced": false
    },
    "0xb83de012dba672c76a7dbbbf3e459cb59d7d6e36": {
      "address": "0xb83de012dba672c76a7dbbbf3e459cb59d7d6e36",
      "first_seen_in_top_ms": 1779007621198,
      "runs_in_top": 291,
      "consecutive_in_top": 13,
      "last_rank": 9,
      "last_seen_ms": 1783632061308,
      "new_entrant_announced": true,
      "drop_off_announced": false
    },
    "0x469e9a7f624b04c24f0e64edf8d8a277e6bf58a5": {
      "address": "0x469e9a7f624b04c24f0e64edf8d8a277e6bf58a5",
      "first_seen_in_top_ms": 1779007621198,
      "runs_in_top": 225,
      "consecutive_in_top": 12,
      "last_rank": 8,
      "last_seen_ms": 1783632061308,
      "new_entrant_announced": true,
      "drop_off_announced": false
    },
    "0x7c930969fcf3e5a5c78bcf2e1cefda3f53e3c8fd": {
      "address": "0x7c930969fcf3e5a5c78bcf2e1cefda3f53e3c8fd",
      "first_seen_in_top_ms": 1779007621198,
      "runs_in_top": 144,
      "consecutive_in_top": 0,
      "last_rank": 50,
      "last_seen_ms": 1781925894868,
      "new_entrant_announced": true,
      "drop_off_announced": true
    },
    "0x77375a8c9d13bf79afb2a87f1b0ac1dfd5f5bf66": {
      "address": "0x77375a8c9d13bf79afb2a87f1b0ac1dfd5f5bf66",
      "first_seen_in_top_ms": 1779007621198,
      "runs_in_top": 292,
      "consecutive_in_top": 292,
      "last_rank": 40,
      "last_seen_ms": 1783632061308,
      "new_entrant_announced": true,
      "drop_off_announced": false
    },
    "0x8af700ba841f30e0a3fcb0ee4c4a9d223e1efa05": {
      "address": "0x8af700ba841f30e0a3fcb0ee4c4a9d223e1efa05",
      "first_seen_in_top_ms": 1779007621198,
      "runs_in_top": 181,
      "consecutive_in_top": 44,
      "last_rank": 5,
      "last_seen_ms": 1783632061308,
      "new_entrant_announced": true,
      "drop_off_announced": false
    },
    "0x5d2f4460ac3514ada79f5d9838916e508ab39bb7": {
      "address": "0x5d2f4460ac3514ada79f5d9838916e508ab39bb7",
      "first_seen_in_top_ms": 1779007621198,
      "runs_in_top": 40,
      "consecutive_in_top": 0,
      "last_rank": 35,
      "last_seen_ms": 1779569247833,
      "new_entrant_announced": true,
      "drop_off_announced": true
    },
    "0x939f95036d2e7b6d7419ec072bf9d967352204d2": {
      "address": "0x939f95036d2e7b6d7419ec072bf9d967352204d2",
      "first_seen_in_top_ms": 1779007621198,
      "runs_in_top": 24,
      "consecutive_in_top": 0,
      "last_rank": 44,
      "last_seen_ms": 1783459252771,
      "new_entrant_announced": true,
      "drop_off_announced": true
    },
    "0x9e8b1e51c642f4c8b87c6ba11c53d516a218afc4": {
      "address": "0x9e8b1e51c642f4c8b87c6ba11c53d516a218afc4",
      "first_seen_in_top_ms": 1779007621198,
      "runs_in_top": 163,
      "consecutive_in_top": 94,
      "last_rank": 3,
      "last_seen_ms": 1783632061308,
      "new_entrant_announced": true,
      "drop_off_announced": false
    },
    "0xa445a0a15b1d50fa0c4bfe6796d9447e0da5329d": {
      "address": "0xa445a0a15b1d50fa0c4bfe6796d9447e0da5329d",
      "first_seen_in_top_ms": 1779007621198,
      "runs_in_top": 149,
      "consecutive_in_top": 53,
      "last_rank": 35,
      "last_seen_ms": 1783632061308,
      "new_entrant_announced": true,
      "drop_off_announced": false
    },
    "0xbf732ea04197942783e34730ed6e0f6099575d58": {
      "address": "0xbf732ea04197942783e34730ed6e0f6099575d58",
      "first_seen_in_top_ms": 1779007621198,
      "runs_in_top": 117,
      "consecutive_in_top": 0,
      "last_rank": 45,
      "last_seen_ms": 1780866602187,
      "new_entrant_announced": true,
      "drop_off_announced": true
    },
    "0x7da85a334e43a6b1c2c0da9623409d9ee9047747": {
      "address": "0x7da85a334e43a6b1c2c0da9623409d9ee9047747",
      "first_seen_in_top_ms": 1779007621198,
      "runs_in_top": 53,
      "consecutive_in_top": 0,
      "last_rank": 48,
      "last_seen_ms": 1780476795044,
      "new_entrant_announced": true,
      "drop_off_announced": true
    },
    "0x1aa780bb10425b86bcf05ecbb7953f9a93729ed9": {
      "address": "0x1aa780bb10425b86bcf05ecbb7953f9a93729ed9",
      "first_seen_in_top_ms": 1779007621198,
      "runs_in_top": 19,
      "consecutive_in_top": 0,
      "last_rank": 41,
      "last_seen_ms": 1779274084700,
      "new_entrant_announced": true,
      "drop_off_announced": true
    },
    "0xaea8e3bd369217cc6e3e6abddf0da318fba8e59b": {
      "address": "0xaea8e3bd369217cc6e3e6abddf0da318fba8e59b",
      "first_seen_in_top_ms": 1779007621198,
      "runs_in_top": 29,
      "consecutive_in_top": 0,
      "last_rank": 47,
      "last_seen_ms": 1782828761413,
      "new_entrant_announced": true,
      "drop_off_announced": true
    },
    "0x6355f7cf36b24044cd5b089a845113327d0ee58e": {
      "address": "0x6355f7cf36b24044cd5b089a845113327d0ee58e",
      "first_seen_in_top_ms": 1779007621198,
      "runs_in_top": 23,
      "consecutive_in_top": 2,
      "last_rank": 45,
      "last_seen_ms": 1783632061308,
      "new_entrant_announced": true,
      "drop_off_announced": false
    },
    "0x45d26f28196d226497130c4bac709d808fed4029": {
      "address": "0x45d26f28196d226497130c4bac709d808fed4029",
      "first_seen_in_top_ms": 1779007621198,
      "runs_in_top": 74,
      "consecutive_in_top": 0,
      "last_rank": 7,
      "last_seen_ms": 1782941135511,
      "new_entrant_announced": true,
      "drop_off_announced": true
    },
    "0x091144e651b334341eabdbbbfed644ad0100023e": {
      "address": "0x091144e651b334341eabdbbbfed644ad0100023e",
      "first_seen_in_top_ms": 1779007621198,
      "runs_in_top": 16,
      "consecutive_in_top": 0,
      "last_rank": 45,
      "last_seen_ms": 1779225474664,
      "new_entrant_announced": true,
      "drop_off_announced": true
    },
    "0x5b5d51203a0f9079f8aeb098a6523a13f298c060": {
      "address": "0x5b5d51203a0f9079f8aeb098a6523a13f298c060",
      "first_seen_in_top_ms": 1779007621198,
      "runs_in_top": 174,
      "consecutive_in_top": 0,
      "last_rank": 47,
      "last_seen_ms": 1783284992192,
      "new_entrant_announced": true,
      "drop_off_announced": true
    },
    "0x48d826da83e69844f2f84b2db50703a933d137a2": {
      "address": "0x48d826da83e69844f2f84b2db50703a933d137a2",
      "first_seen_in_top_ms": 1779007621198,
      "runs_in_top": 69,
      "consecutive_in_top": 1,
      "last_rank": 49,
      "last_seen_ms": 1783632061308,
      "new_entrant_announced": true,
      "drop_off_announced": false
    },
    "0x015354106478dda69c4aae3c0cf801290b738052": {
      "address": "0x015354106478dda69c4aae3c0cf801290b738052",
      "first_seen_in_top_ms": 1779007621198,
      "runs_in_top": 17,
      "consecutive_in_top": 0,
      "last_rank": 47,
      "last_seen_ms": 1779313818996,
      "new_entrant_announced": true,
      "drop_off_announced": true
    },
    "0xdf9ea6ec3b7109935ccb4fb267e15ac1fb077ab1": {
      "address": "0xdf9ea6ec3b7109935ccb4fb267e15ac1fb077ab1",
      "first_seen_in_top_ms": 1779007621198,
      "runs_in_top": 25,
      "consecutive_in_top": 6,
      "last_rank": 42,
      "last_seen_ms": 1783632061308,
      "new_entrant_announced": true,
      "drop_off_announced": false
    },
    "0xdd7a372377fc633f74ab6e20963803d52f448830": {
      "address": "0xdd7a372377fc633f74ab6e20963803d52f448830",
      "first_seen_in_top_ms": 1779007621198,
      "runs_in_top": 17,
      "consecutive_in_top": 0,
      "last_rank": 48,
      "last_seen_ms": 1779831749044,
      "new_entrant_announced": true,
      "drop_off_announced": true
    },
    "0x795cfd1b03eafc11c4ec958b8a94cfc9aa64a242": {
      "address": "0x795cfd1b03eafc11c4ec958b8a94cfc9aa64a242",
      "first_seen_in_top_ms": 1779007621198,
      "runs_in_top": 113,
      "consecutive_in_top": 0,
      "last_rank": 43,
      "last_seen_ms": 1781733552728,
      "new_entrant_announced": true,
      "drop_off_announced": true
    },
    "0x152e41f0b83e6cad4b5dc730c1d6279b7d67c9dc": {
      "address": "0x152e41f0b83e6cad4b5dc730c1d6279b7d67c9dc",
      "first_seen_in_top_ms": 1779007621198,
      "runs_in_top": 205,
      "consecutive_in_top": 93,
      "last_rank": 14,
      "last_seen_ms": 1783632061308,
      "new_entrant_announced": true,
      "drop_off_announced": false
    },
    "0xaf0fdd39e5d92499b0ed9f68693da99c0ec1e92e": {
      "address": "0xaf0fdd39e5d92499b0ed9f68693da99c0ec1e92e",
      "first_seen_in_top_ms": 1779007621198,
      "runs_in_top": 214,
      "consecutive_in_top": 77,
      "last_rank": 19,
      "last_seen_ms": 1783632061308,
      "new_entrant_announced": true,
      "drop_off_announced": false
    },
    "0x888e000c78b8f1aada5b3c99f880794907b76d77": {
      "address": "0x888e000c78b8f1aada5b3c99f880794907b76d77",
      "first_seen_in_top_ms": 1779007621198,
      "runs_in_top": 9,
      "consecutive_in_top": 0,
      "last_rank": 47,
      "last_seen_ms": 1779127142128,
      "new_entrant_announced": true,
      "drop_off_announced": false
    },
    "0x8ea85cbd59affca28162fc286d5c093dd0f8edbc": {
      "address": "0x8ea85cbd59affca28162fc286d5c093dd0f8edbc",
      "first_seen_in_top_ms": 1779007621198,
      "runs_in_top": 5,
      "consecutive_in_top": 0,
      "last_rank": 32,
      "last_seen_ms": 1779050830608,
      "new_entrant_announced": true,
      "drop_off_announced": false
    },
    "0x5559da6ec434c5723d0ce9c4da7f29e3f8a3d43b": {
      "address": "0x5559da6ec434c5723d0ce9c4da7f29e3f8a3d43b",
      "first_seen_in_top_ms": 1779007621198,
      "runs_in_top": 63,
      "consecutive_in_top": 0,
      "last_rank": 39,
      "last_seen_ms": 1781215232950,
      "new_entrant_announced": true,
      "drop_off_announced": true
    },
    "0xcac19662ec88d23fa1c81ac0e8570b0cf2ff26b3": {
      "address": "0xcac19662ec88d23fa1c81ac0e8570b0cf2ff26b3",
      "first_seen_in_top_ms": 1779007621198,
      "runs_in_top": 45,
      "consecutive_in_top": 0,
      "last_rank": 18,
      "last_seen_ms": 1783198415220,
      "new_entrant_announced": true,
      "drop_off_announced": true
    },
    "0x007d76eec0ba411ce873a8819df50dd443d967a0": {
      "address": "0x007d76eec0ba411ce873a8819df50dd443d967a0",
      "first_seen_in_top_ms": 1779007621198,
      "runs_in_top": 51,
      "consecutive_in_top": 0,
      "last_rank": 46,
      "last_seen_ms": 1782460130998,
      "new_entrant_announced": true,
      "drop_off_announced": true
    },
    "0x92b75a5bfb7be7911747276ad335b8f5da3ce0f4": {
      "address": "0x92b75a5bfb7be7911747276ad335b8f5da3ce0f4",
      "first_seen_in_top_ms": 1779007621198,
      "runs_in_top": 5,
      "consecutive_in_top": 0,
      "last_rank": 40,
      "last_seen_ms": 1779050830608,
      "new_entrant_announced": true,
      "drop_off_announced": false
    },
    "0x5bc43f38c2ddcd85857f218674cd384f172c3b0c": {
      "address": "0x5bc43f38c2ddcd85857f218674cd384f172c3b0c",
      "first_seen_in_top_ms": 1779007621198,
      "runs_in_top": 10,
      "consecutive_in_top": 0,
      "last_rank": 46,
      "last_seen_ms": 1779138575260,
      "new_entrant_announced": true,
      "drop_off_announced": true
    },
    "0xea0027b6ea9b6d7d401b5266979cc3b3ca87a918": {
      "address": "0xea0027b6ea9b6d7d401b5266979cc3b3ca87a918",
      "first_seen_in_top_ms": 1779007621198,
      "runs_in_top": 10,
      "consecutive_in_top": 0,
      "last_rank": 48,
      "last_seen_ms": 1779159369195,
      "new_entrant_announced": true,
      "drop_off_announced": true
    },
    "0x2d99fe0f36c1aebd28a1a2c0e82e8ca13c2ea351": {
      "address": "0x2d99fe0f36c1aebd28a1a2c0e82e8ca13c2ea351",
      "first_seen_in_top_ms": 1779007621198,
      "runs_in_top": 15,
      "consecutive_in_top": 0,
      "last_rank": 41,
      "last_seen_ms": 1783198415220,
      "new_entrant_announced": true,
      "drop_off_announced": true
    },
    "0x66466428990e0f42a4c54f64bee0db6bf2336de5": {
      "address": "0x66466428990e0f42a4c54f64bee0db6bf2336de5",
      "first_seen_in_top_ms": 1779007621198,
      "runs_in_top": 5,
      "consecutive_in_top": 0,
      "last_rank": 46,
      "last_seen_ms": 1779050830608,
      "new_entrant_announced": true,
      "drop_off_announced": false
    },
    "0xdbcc96bcada067864902aad14e029fe7c422f147": {
      "address": "0xdbcc96bcada067864902aad14e029fe7c422f147",
      "first_seen_in_top_ms": 1779007621198,
      "runs_in_top": 5,
      "consecutive_in_top": 0,
      "last_rank": 49,
      "last_seen_ms": 1779050830608,
      "new_entrant_announced": true,
      "drop_off_announced": false
    },
    "0x8cc94dc843e1ea7a19805e0cca43001123512b6a": {
      "address": "0x8cc94dc843e1ea7a19805e0cca43001123512b6a",
      "first_seen_in_top_ms": 1779007621198,
      "runs_in_top": 130,
      "consecutive_in_top": 0,
      "last_rank": 44,
      "last_seen_ms": 1783074760872,
      "new_entrant_announced": true,
      "drop_off_announced": true
    },
    "0x85ecf584f25db6f146718b86d493e33c5af72052": {
      "address": "0x85ecf584f25db6f146718b86d493e33c5af72052",
      "first_seen_in_top_ms": 1779007621198,
      "runs_in_top": 114,
      "consecutive_in_top": 0,
      "last_rank": 45,
      "last_seen_ms": 1781385160963,
      "new_entrant_announced": true,
      "drop_off_announced": true
    },
    "0x8bae3527e5a33fa0cf184f37bc112d071463ab6d": {
      "address": "0x8bae3527e5a33fa0cf184f37bc112d071463ab6d",
      "first_seen_in_top_ms": 1779007621198,
      "runs_in_top": 13,
      "consecutive_in_top": 0,
      "last_rank": 50,
      "last_seen_ms": 1779213808299,
      "new_entrant_announced": true,
      "drop_off_announced": true
    },
    "0x399965e15d4e61ec3529cc98b7f7ebb93b733336": {
      "address": "0x399965e15d4e61ec3529cc98b7f7ebb93b733336",
      "first_seen_in_top_ms": 1779007621198,
      "runs_in_top": 173,
      "consecutive_in_top": 29,
      "last_rank": 26,
      "last_seen_ms": 1783632061308,
      "new_entrant_announced": true,
      "drop_off_announced": false
    },
    "0xd260b2216b735277da6771564a01c04856e78321": {
      "address": "0xd260b2216b735277da6771564a01c04856e78321",
      "first_seen_in_top_ms": 1779007621198,
      "runs_in_top": 4,
      "consecutive_in_top": 0,
      "last_rank": 48,
      "last_seen_ms": 1779036901671,
      "new_entrant_announced": true,
      "drop_off_announced": false
    },
    "0xf17de447fdfa1778db06111e3cbdc878332adab2": {
      "address": "0xf17de447fdfa1778db06111e3cbdc878332adab2",
      "first_seen_in_top_ms": 1779007621198,
      "runs_in_top": 20,
      "consecutive_in_top": 0,
      "last_rank": 50,
      "last_seen_ms": 1779517931350,
      "new_entrant_announced": true,
      "drop_off_announced": true
    },
    "0xf517639a8872e756ac98d3c65507d2ebc25cc032": {
      "address": "0xf517639a8872e756ac98d3c65507d2ebc25cc032",
      "first_seen_in_top_ms": 1779007621198,
      "runs_in_top": 85,
      "consecutive_in_top": 0,
      "last_rank": 39,
      "last_seen_ms": 1783284992192,
      "new_entrant_announced": true,
      "drop_off_announced": true
    },
    "0xe091330c53b971ed4e886f902f18e8544a8d6705": {
      "address": "0xe091330c53b971ed4e886f902f18e8544a8d6705",
      "first_seen_in_top_ms": 1779007621198,
      "runs_in_top": 3,
      "consecutive_in_top": 0,
      "last_rank": 49,
      "last_seen_ms": 1779023706434,
      "new_entrant_announced": true,
      "drop_off_announced": false
    },
    "0x7fa77093e83c9292c2357ea799ac2c57ec138203": {
      "address": "0x7fa77093e83c9292c2357ea799ac2c57ec138203",
      "first_seen_in_top_ms": 1779036901671,
      "runs_in_top": 1,
      "consecutive_in_top": 0,
      "last_rank": 50,
      "last_seen_ms": 1779036901671,
      "new_entrant_announced": false,
      "drop_off_announced": false
    },
    "0xe867fbdad3291530e41530301ecb77693850c78e": {
      "address": "0xe867fbdad3291530e41530301ecb77693850c78e",
      "first_seen_in_top_ms": 1779050830608,
      "runs_in_top": 282,
      "consecutive_in_top": 60,
      "last_rank": 2,
      "last_seen_ms": 1783632061308,
      "new_entrant_announced": true,
      "drop_off_announced": false
    },
    "0x03b9a189e2480d1e4c3007080b29f362282130fa": {
      "address": "0x03b9a189e2480d1e4c3007080b29f362282130fa",
      "first_seen_in_top_ms": 1779050830608,
      "runs_in_top": 242,
      "consecutive_in_top": 29,
      "last_rank": 6,
      "last_seen_ms": 1783632061308,
      "new_entrant_announced": true,
      "drop_off_announced": false
    },
    "0xa0d66bab5f04cb3055cc2f6b0494cb33be32c2c2": {
      "address": "0xa0d66bab5f04cb3055cc2f6b0494cb33be32c2c2",
      "first_seen_in_top_ms": 1779050830608,
      "runs_in_top": 94,
      "consecutive_in_top": 0,
      "last_rank": 48,
      "last_seen_ms": 1783477594192,
      "new_entrant_announced": true,
      "drop_off_announced": true
    },
    "0xdcac85ecae7148886029c20e661d848a4de99ce2": {
      "address": "0xdcac85ecae7148886029c20e661d848a4de99ce2",
      "first_seen_in_top_ms": 1779050830608,
      "runs_in_top": 189,
      "consecutive_in_top": 0,
      "last_rank": 50,
      "last_seen_ms": 1783087001439,
      "new_entrant_announced": true,
      "drop_off_announced": true
    },
    "0x87f9cd15f5050a9283b8896300f7c8cf69ece2cf": {
      "address": "0x87f9cd15f5050a9283b8896300f7c8cf69ece2cf",
      "first_seen_in_top_ms": 1779050830608,
      "runs_in_top": 259,
      "consecutive_in_top": 0,
      "last_rank": 46,
      "last_seen_ms": 1783544638274,
      "new_entrant_announced": true,
      "drop_off_announced": true
    },
    "0xb8ebd6ed57f4102be5b1caf60d01dd1c9f270f94": {
      "address": "0xb8ebd6ed57f4102be5b1caf60d01dd1c9f270f94",
      "first_seen_in_top_ms": 1779050830608,
      "runs_in_top": 189,
      "consecutive_in_top": 29,
      "last_rank": 25,
      "last_seen_ms": 1783632061308,
      "new_entrant_announced": true,
      "drop_off_announced": false
    },
    "0x7be1cba648ebe1ab8084244d23f28d68a86480d8": {
      "address": "0x7be1cba648ebe1ab8084244d23f28d68a86480d8",
      "first_seen_in_top_ms": 1779050830608,
      "runs_in_top": 215,
      "consecutive_in_top": 0,
      "last_rank": 49,
      "last_seen_ms": 1783582473394,
      "new_entrant_announced": true,
      "drop_off_announced": true
    },
    "0xa03236e2daca8f5583bd4654a0f2c9d96c6702aa": {
      "address": "0xa03236e2daca8f5583bd4654a0f2c9d96c6702aa",
      "first_seen_in_top_ms": 1779050830608,
      "runs_in_top": 20,
      "consecutive_in_top": 0,
      "last_rank": 43,
      "last_seen_ms": 1781903268559,
      "new_entrant_announced": true,
      "drop_off_announced": true
    },
    "0x94dac1facdc4afd2614c3119447187b4143bc449": {
      "address": "0x94dac1facdc4afd2614c3119447187b4143bc449",
      "first_seen_in_top_ms": 1779050830608,
      "runs_in_top": 109,
      "consecutive_in_top": 0,
      "last_rank": 49,
      "last_seen_ms": 1781903268559,
      "new_entrant_announced": true,
      "drop_off_announced": true
    },
    "0x7839e2f2c375dd2935193f2736167514efff9916": {
      "address": "0x7839e2f2c375dd2935193f2736167514efff9916",
      "first_seen_in_top_ms": 1779050830608,
      "runs_in_top": 220,
      "consecutive_in_top": 44,
      "last_rank": 22,
      "last_seen_ms": 1783632061308,
      "new_entrant_announced": true,
      "drop_off_announced": false
    },
    "0x218a65e21eddeece7a9df38c6bbdd89f692b7da2": {
      "address": "0x218a65e21eddeece7a9df38c6bbdd89f692b7da2",
      "first_seen_in_top_ms": 1779074823526,
      "runs_in_top": 205,
      "consecutive_in_top": 12,
      "last_rank": 30,
      "last_seen_ms": 1783632061308,
      "new_entrant_announced": true,
      "drop_off_announced": false
    },
    "0x7717a7a245d9f950e586822b8c9b46863ed7bd7e": {
      "address": "0x7717a7a245d9f950e586822b8c9b46863ed7bd7e",
      "first_seen_in_top_ms": 1779074823526,
      "runs_in_top": 125,
      "consecutive_in_top": 0,
      "last_rank": 48,
      "last_seen_ms": 1783026125322,
      "new_entrant_announced": true,
      "drop_off_announced": true
    },
    "0x523852be2db1a76a0e088ecbff32e849544054e5": {
      "address": "0x523852be2db1a76a0e088ecbff32e849544054e5",
      "first_seen_in_top_ms": 1779074823526,
      "runs_in_top": 28,
      "consecutive_in_top": 0,
      "last_rank": 45,
      "last_seen_ms": 1779484046343,
      "new_entrant_announced": true,
      "drop_off_announced": true
    },
    "0x0b00c540bc5f203d97ac87da62164d3d37e19798": {
      "address": "0x0b00c540bc5f203d97ac87da62164d3d37e19798",
      "first_seen_in_top_ms": 1779074823526,
      "runs_in_top": 5,
      "consecutive_in_top": 0,
      "last_rank": 43,
      "last_seen_ms": 1779138575260,
      "new_entrant_announced": true,
      "drop_off_announced": false
    },
    "0x2d23b731e5f04996a2dfdbe434c7d922afdb5e00": {
      "address": "0x2d23b731e5f04996a2dfdbe434c7d922afdb5e00",
      "first_seen_in_top_ms": 1779074823526,
      "runs_in_top": 121,
      "consecutive_in_top": 0,
      "last_rank": 42,
      "last_seen_ms": 1783564860320,
      "new_entrant_announced": true,
      "drop_off_announced": true
    },
    "0x99b1098d9d50aa076f78bd26ab22e6abd3710729": {
      "address": "0x99b1098d9d50aa076f78bd26ab22e6abd3710729",
      "first_seen_in_top_ms": 1779074823526,
      "runs_in_top": 13,
      "consecutive_in_top": 0,
      "last_rank": 44,
      "last_seen_ms": 1782397594864,
      "new_entrant_announced": true,
      "drop_off_announced": true
    },
    "0x00f8da96829820da934fc4a4cb7d39031ce7454b": {
      "address": "0x00f8da96829820da934fc4a4cb7d39031ce7454b",
      "first_seen_in_top_ms": 1779074823526,
      "runs_in_top": 7,
      "consecutive_in_top": 0,
      "last_rank": 35,
      "last_seen_ms": 1779225474664,
      "new_entrant_announced": true,
      "drop_off_announced": false
    },
    "0xe2f86feccb1207710a442bc4e27a0701a290275a": {
      "address": "0xe2f86feccb1207710a442bc4e27a0701a290275a",
      "first_seen_in_top_ms": 1779074823526,
      "runs_in_top": 34,
      "consecutive_in_top": 0,
      "last_rank": 48,
      "last_seen_ms": 1779808765000,
      "new_entrant_announced": true,
      "drop_off_announced": true
    },
    "0x6fa6f42d2e41327e27fe7f416a823cef7050825e": {
      "address": "0x6fa6f42d2e41327e27fe7f416a823cef7050825e",
      "first_seen_in_top_ms": 1779074823526,
      "runs_in_top": 3,
      "consecutive_in_top": 0,
      "last_rank": 50,
      "last_seen_ms": 1779127142128,
      "new_entrant_announced": false,
      "drop_off_announced": false
    },
    "0x3440f23a87f1950e7a88cd248fd270e92d1132c5": {
      "address": "0x3440f23a87f1950e7a88cd248fd270e92d1132c5",
      "first_seen_in_top_ms": 1779091224792,
      "runs_in_top": 62,
      "consecutive_in_top": 0,
      "last_rank": 50,
      "last_seen_ms": 1783000365982,
      "new_entrant_announced": true,
      "drop_off_announced": true
    },
    "0x8ed318c5eefd8c9b15b6ee351734c8a350b2f23a": {
      "address": "0x8ed318c5eefd8c9b15b6ee351734c8a350b2f23a",
      "first_seen_in_top_ms": 1779127142128,
      "runs_in_top": 7,
      "consecutive_in_top": 6,
      "last_rank": 47,
      "last_seen_ms": 1783632061308,
      "new_entrant_announced": true,
      "drop_off_announced": false
    },
    "0x20c2d95a3dfdca9e9ad12794d5fa6fad99da44f5": {
      "address": "0x20c2d95a3dfdca9e9ad12794d5fa6fad99da44f5",
      "first_seen_in_top_ms": 1779138575260,
      "runs_in_top": 1,
      "consecutive_in_top": 0,
      "last_rank": 27,
      "last_seen_ms": 1779138575260,
      "new_entrant_announced": false,
      "drop_off_announced": false
    },
    "0x9321d8117e73b0c79035f0e87debcfd8dbb1d75a": {
      "address": "0x9321d8117e73b0c79035f0e87debcfd8dbb1d75a",
      "first_seen_in_top_ms": 1779159369195,
      "runs_in_top": 219,
      "consecutive_in_top": 0,
      "last_rank": 50,
      "last_seen_ms": 1782841812188,
      "new_entrant_announced": true,
      "drop_off_announced": true
    },
    "0xfc84a4bba95d3a13f91a9c0d735c0af04a18f4d0": {
      "address": "0xfc84a4bba95d3a13f91a9c0d735c0af04a18f4d0",
      "first_seen_in_top_ms": 1779176590667,
      "runs_in_top": 21,
      "consecutive_in_top": 0,
      "last_rank": 39,
      "last_seen_ms": 1779484046343,
      "new_entrant_announced": true,
      "drop_off_announced": true
    },
    "0x462e3f2ce774b4dbba10662a2155e4823d4c820f": {
      "address": "0x462e3f2ce774b4dbba10662a2155e4823d4c820f",
      "first_seen_in_top_ms": 1779202546530,
      "runs_in_top": 183,
      "consecutive_in_top": 0,
      "last_rank": 36,
      "last_seen_ms": 1783544638274,
      "new_entrant_announced": true,
      "drop_off_announced": true
    },
    "0xd6e56265890b76413d1d527eb9b75e334c0c5b42": {
      "address": "0xd6e56265890b76413d1d527eb9b75e334c0c5b42",
      "first_seen_in_top_ms": 1779202546530,
      "runs_in_top": 102,
      "consecutive_in_top": 0,
      "last_rank": 48,
      "last_seen_ms": 1781385160963,
      "new_entrant_announced": true,
      "drop_off_announced": true
    },
    "0x519c721de735f7c9e6146d167852e60d60496a47": {
      "address": "0x519c721de735f7c9e6146d167852e60d60496a47",
      "first_seen_in_top_ms": 1779245794837,
      "runs_in_top": 176,
      "consecutive_in_top": 0,
      "last_rank": 36,
      "last_seen_ms": 1782165624086,
      "new_entrant_announced": true,
      "drop_off_announced": true
    },
    "0x96de02546bde61e6a62e3f242ea4c55265311445": {
      "address": "0x96de02546bde61e6a62e3f242ea4c55265311445",
      "first_seen_in_top_ms": 1779245794837,
      "runs_in_top": 74,
      "consecutive_in_top": 0,
      "last_rank": 23,
      "last_seen_ms": 1781519347192,
      "new_entrant_announced": true,
      "drop_off_announced": true
    },
    "0xaefcc9cacbe0e41978bef1818358f471848de9cb": {
      "address": "0xaefcc9cacbe0e41978bef1818358f471848de9cb",
      "first_seen_in_top_ms": 1779245794837,
      "runs_in_top": 123,
      "consecutive_in_top": 0,
      "last_rank": 47,
      "last_seen_ms": 1781820296530,
      "new_entrant_announced": true,
      "drop_off_announced": true
    },
    "0x36874c195c02152a42e8db30c7053b71d7342067": {
      "address": "0x36874c195c02152a42e8db30c7053b71d7342067",
      "first_seen_in_top_ms": 1779245794837,
      "runs_in_top": 43,
      "consecutive_in_top": 0,
      "last_rank": 38,
      "last_seen_ms": 1780779694718,
      "new_entrant_announced": true,
      "drop_off_announced": true
    },
    "0x89c645ecbd07825b194e3b98300eb3497aaba406": {
      "address": "0x89c645ecbd07825b194e3b98300eb3497aaba406",
      "first_seen_in_top_ms": 1779245794837,
      "runs_in_top": 139,
      "consecutive_in_top": 0,
      "last_rank": 40,
      "last_seen_ms": 1783544638274,
      "new_entrant_announced": true,
      "drop_off_announced": true
    },
    "0xa1830e8d9f019feb448478a171bb37cc6c4c0482": {
      "address": "0xa1830e8d9f019feb448478a171bb37cc6c4c0482",
      "first_seen_in_top_ms": 1779262873936,
      "runs_in_top": 12,
      "consecutive_in_top": 0,
      "last_rank": 39,
      "last_seen_ms": 1779460445253,
      "new_entrant_announced": true,
      "drop_off_announced": true
    },
    "0xf5629393e446a103a4be1c49a956255e7c87c1d3": {
      "address": "0xf5629393e446a103a4be1c49a956255e7c87c1d3",
      "first_seen_in_top_ms": 1779289048776,
      "runs_in_top": 3,
      "consecutive_in_top": 0,
      "last_rank": 36,
      "last_seen_ms": 1779313818996,
      "new_entrant_announced": true,
      "drop_off_announced": false
    },
    "0x0871deb34bfd2052b1c10dc4f6c0912a2a47e927": {
      "address": "0x0871deb34bfd2052b1c10dc4f6c0912a2a47e927",
      "first_seen_in_top_ms": 1779289048776,
      "runs_in_top": 78,
      "consecutive_in_top": 0,
      "last_rank": 49,
      "last_seen_ms": 1783531559877,
      "new_entrant_announced": true,
      "drop_off_announced": true
    },
    "0xff4cd3826ecee12acd4329aada4a2d3419fc463c": {
      "address": "0xff4cd3826ecee12acd4329aada4a2d3419fc463c",
      "first_seen_in_top_ms": 1779289048776,
      "runs_in_top": 196,
      "consecutive_in_top": 0,
      "last_rank": 44,
      "last_seen_ms": 1782941135511,
      "new_entrant_announced": true,
      "drop_off_announced": true
    },
    "0xa4dedda59f2908b92ae192cfd494839373bcb3c4": {
      "address": "0xa4dedda59f2908b92ae192cfd494839373bcb3c4",
      "first_seen_in_top_ms": 1779289048776,
      "runs_in_top": 164,
      "consecutive_in_top": 0,
      "last_rank": 49,
      "last_seen_ms": 1783446988421,
      "new_entrant_announced": true,
      "drop_off_announced": true
    },
    "0xe639710e64d7094f7f82ab495915559c2f612953": {
      "address": "0xe639710e64d7094f7f82ab495915559c2f612953",
      "first_seen_in_top_ms": 1779300862592,
      "runs_in_top": 9,
      "consecutive_in_top": 0,
      "last_rank": 45,
      "last_seen_ms": 1779420304981,
      "new_entrant_announced": true,
      "drop_off_announced": false
    },
    "0x6ba889db7f923622d3548f621ecc2054b80c1817": {
      "address": "0x6ba889db7f923622d3548f621ecc2054b80c1817",
      "first_seen_in_top_ms": 1779333909489,
      "runs_in_top": 89,
      "consecutive_in_top": 0,
      "last_rank": 43,
      "last_seen_ms": 1783477594192,
      "new_entrant_announced": true,
      "drop_off_announced": true
    },
    "0x1367df28c0681431b8a8f3d887576a1cad85560e": {
      "address": "0x1367df28c0681431b8a8f3d887576a1cad85560e",
      "first_seen_in_top_ms": 1779333909489,
      "runs_in_top": 78,
      "consecutive_in_top": 0,
      "last_rank": 40,
      "last_seen_ms": 1780630236966,
      "new_entrant_announced": true,
      "drop_off_announced": true
    },
    "0xeee0d806e4f0a427277433d6b580619918770b53": {
      "address": "0xeee0d806e4f0a427277433d6b580619918770b53",
      "first_seen_in_top_ms": 1779333909489,
      "runs_in_top": 6,
      "consecutive_in_top": 0,
      "last_rank": 47,
      "last_seen_ms": 1783198415220,
      "new_entrant_announced": false,
      "drop_off_announced": false
    },
    "0xd2b2a8ab7a8c903501f4db4ee45c67522a4511ed": {
      "address": "0xd2b2a8ab7a8c903501f4db4ee45c67522a4511ed",
      "first_seen_in_top_ms": 1779333909489,
      "runs_in_top": 12,
      "consecutive_in_top": 0,
      "last_rank": 50,
      "last_seen_ms": 1779743038500,
      "new_entrant_announced": true,
      "drop_off_announced": true
    },
    "0x4d470e0a241c3d7321b4b6c6f23f214db85bfa47": {
      "address": "0x4d470e0a241c3d7321b4b6c6f23f214db85bfa47",
      "first_seen_in_top_ms": 1779333909489,
      "runs_in_top": 81,
      "consecutive_in_top": 0,
      "last_rank": 48,
      "last_seen_ms": 1781733552728,
      "new_entrant_announced": true,
      "drop_off_announced": true
    },
    "0x8f8d2d2565bfb10608a7ce64b48e2aea7875a344": {
      "address": "0x8f8d2d2565bfb10608a7ce64b48e2aea7875a344",
      "first_seen_in_top_ms": 1779333909489,
      "runs_in_top": 31,
      "consecutive_in_top": 0,
      "last_rank": 50,
      "last_seen_ms": 1780222385494,
      "new_entrant_announced": true,
      "drop_off_announced": true
    },
    "0x92ae4209e3a5760903aff0c423312392eb3f86a8": {
      "address": "0x92ae4209e3a5760903aff0c423312392eb3f86a8",
      "first_seen_in_top_ms": 1779333909489,
      "runs_in_top": 33,
      "consecutive_in_top": 0,
      "last_rank": 50,
      "last_seen_ms": 1780234797376,
      "new_entrant_announced": true,
      "drop_off_announced": true
    },
    "0x13c50dcdee4bbcba71baf578b345cdd35c7928be": {
      "address": "0x13c50dcdee4bbcba71baf578b345cdd35c7928be",
      "first_seen_in_top_ms": 1779349667544,
      "runs_in_top": 122,
      "consecutive_in_top": 0,
      "last_rank": 5,
      "last_seen_ms": 1781300498148,
      "new_entrant_announced": true,
      "drop_off_announced": true
    },
    "0xc926ddba8b7617dbc65712f20cf8e1b58b8598d3": {
      "address": "0xc926ddba8b7617dbc65712f20cf8e1b58b8598d3",
      "first_seen_in_top_ms": 1779349667544,
      "runs_in_top": 201,
      "consecutive_in_top": 94,
      "last_rank": 18,
      "last_seen_ms": 1783632061308,
      "new_entrant_announced": true,
      "drop_off_announced": false
    },
    "0x47a127f496d001f187ac65fc24852274dc51d080": {
      "address": "0x47a127f496d001f187ac65fc24852274dc51d080",
      "first_seen_in_top_ms": 1779362427252,
      "runs_in_top": 47,
      "consecutive_in_top": 0,
      "last_rank": 49,
      "last_seen_ms": 1781733552728,
      "new_entrant_announced": true,
      "drop_off_announced": true
    },
    "0xceec48581b3145a575508719f45da07dc57fa7ce": {
      "address": "0xceec48581b3145a575508719f45da07dc57fa7ce",
      "first_seen_in_top_ms": 1779386077005,
      "runs_in_top": 124,
      "consecutive_in_top": 0,
      "last_rank": 47,
      "last_seen_ms": 1782165624086,
      "new_entrant_announced": true,
      "drop_off_announced": true
    },
    "0x23afa6c8b67f9dda2751254e8be260ccb950e2c0": {
      "address": "0x23afa6c8b67f9dda2751254e8be260ccb950e2c0",
      "first_seen_in_top_ms": 1779435709465,
      "runs_in_top": 3,
      "consecutive_in_top": 0,
      "last_rank": 49,
      "last_seen_ms": 1779484046343,
      "new_entrant_announced": false,
      "drop_off_announced": false
    },
    "0x0f991873aab3e14191978946d48f30f624ae9867": {
      "address": "0x0f991873aab3e14191978946d48f30f624ae9867",
      "first_seen_in_top_ms": 1779446869335,
      "runs_in_top": 159,
      "consecutive_in_top": 0,
      "last_rank": 24,
      "last_seen_ms": 1782076267674,
      "new_entrant_announced": true,
      "drop_off_announced": true
    },
    "0xaeae3319f670f1f7aa18b42f9d5f3452f4ee69e6": {
      "address": "0xaeae3319f670f1f7aa18b42f9d5f3452f4ee69e6",
      "first_seen_in_top_ms": 1779460445253,
      "runs_in_top": 24,
      "consecutive_in_top": 0,
      "last_rank": 23,
      "last_seen_ms": 1780305854521,
      "new_entrant_announced": true,
      "drop_off_announced": true
    },
    "0x1e48f1007fa133f643941d58cb6b080dc621e773": {
      "address": "0x1e48f1007fa133f643941d58cb6b080dc621e773",
      "first_seen_in_top_ms": 1779460445253,
      "runs_in_top": 8,
      "consecutive_in_top": 0,
      "last_rank": 34,
      "last_seen_ms": 1779555418654,
      "new_entrant_announced": true,
      "drop_off_announced": false
    },
    "0xb798aef79972ce8f73d47b9ebbcda6bbb7ec4fbf": {
      "address": "0xb798aef79972ce8f73d47b9ebbcda6bbb7ec4fbf",
      "first_seen_in_top_ms": 1779529769162,
      "runs_in_top": 68,
      "consecutive_in_top": 0,
      "last_rank": 29,
      "last_seen_ms": 1783112508380,
      "new_entrant_announced": true,
      "drop_off_announced": true
    },
    "0xfb941d2344b72ea9101400392b818173772d0ddf": {
      "address": "0xfb941d2344b72ea9101400392b818173772d0ddf",
      "first_seen_in_top_ms": 1779591464190,
      "runs_in_top": 119,
      "consecutive_in_top": 23,
      "last_rank": 34,
      "last_seen_ms": 1783632061308,
      "new_entrant_announced": true,
      "drop_off_announced": false
    },
    "0x0320e2787d5c62a4a81f219dfb3c5abdf6265362": {
      "address": "0x0320e2787d5c62a4a81f219dfb3c5abdf6265362",
      "first_seen_in_top_ms": 1779628826345,
      "runs_in_top": 80,
      "consecutive_in_top": 0,
      "last_rank": 46,
      "last_seen_ms": 1781647734934,
      "new_entrant_announced": true,
      "drop_off_announced": true
    },
    "0x77746ff04a7014752ab12d81d531aa5e50775343": {
      "address": "0x77746ff04a7014752ab12d81d531aa5e50775343",
      "first_seen_in_top_ms": 1779628826345,
      "runs_in_top": 23,
      "consecutive_in_top": 0,
      "last_rank": 50,
      "last_seen_ms": 1781753933597,
      "new_entrant_announced": true,
      "drop_off_announced": true
    },
    "0x0aadc54a9e78cfe2e971aa8edcedea9c6df01f46": {
      "address": "0x0aadc54a9e78cfe2e971aa8edcedea9c6df01f46",
      "first_seen_in_top_ms": 1779641857035,
      "runs_in_top": 155,
      "consecutive_in_top": 0,
      "last_rank": 47,
      "last_seen_ms": 1782250889465,
      "new_entrant_announced": true,
      "drop_off_announced": true
    },
    "0xefba0f56eef05f6a7d614ce519d2e284b46d3583": {
      "address": "0xefba0f56eef05f6a7d614ce519d2e284b46d3583",
      "first_seen_in_top_ms": 1779730884664,
      "runs_in_top": 2,
      "consecutive_in_top": 0,
      "last_rank": 50,
      "last_seen_ms": 1779808765000,
      "new_entrant_announced": false,
      "drop_off_announced": false
    },
    "0x15271757b398cd1d3d7cca05c4f7b0c159afa7c2": {
      "address": "0x15271757b398cd1d3d7cca05c4f7b0c159afa7c2",
      "first_seen_in_top_ms": 1779852754304,
      "runs_in_top": 66,
      "consecutive_in_top": 0,
      "last_rank": 50,
      "last_seen_ms": 1781471330371,
      "new_entrant_announced": true,
      "drop_off_announced": true
    },
    "0x005844b2ffb2e122cf4244be7dbcb4f84924907c": {
      "address": "0x005844b2ffb2e122cf4244be7dbcb4f84924907c",
      "first_seen_in_top_ms": 1779868847951,
      "runs_in_top": 22,
      "consecutive_in_top": 0,
      "last_rank": 49,
      "last_seen_ms": 1780353133232,
      "new_entrant_announced": true,
      "drop_off_announced": true
    },
    "0x0ddf9bae2af4b874b96d287a5ad42eb47138a902": {
      "address": "0x0ddf9bae2af4b874b96d287a5ad42eb47138a902",
      "first_seen_in_top_ms": 1779896090139,
      "runs_in_top": 158,
      "consecutive_in_top": 0,
      "last_rank": 22,
      "last_seen_ms": 1783171099667,
      "new_entrant_announced": true,
      "drop_off_announced": true
    },
    "0x5f94a51948d2376ad34a6fadfa2544e651b74b96": {
      "address": "0x5f94a51948d2376ad34a6fadfa2544e651b74b96",
      "first_seen_in_top_ms": 1779918736764,
      "runs_in_top": 149,
      "consecutive_in_top": 0,
      "last_rank": 30,
      "last_seen_ms": 1783544638274,
      "new_entrant_announced": true,
      "drop_off_announced": true
    },
    "0x17a4ce9320bec0ac79420f0af19848044a469d8d": {
      "address": "0x17a4ce9320bec0ac79420f0af19848044a469d8d",
      "first_seen_in_top_ms": 1780041165710,
      "runs_in_top": 195,
      "consecutive_in_top": 29,
      "last_rank": 20,
      "last_seen_ms": 1783632061308,
      "new_entrant_announced": true,
      "drop_off_announced": false
    },
    "0x992ec71207c9e183e64c81461908f1a1a783af6a": {
      "address": "0x992ec71207c9e183e64c81461908f1a1a783af6a",
      "first_seen_in_top_ms": 1780079428444,
      "runs_in_top": 97,
      "consecutive_in_top": 0,
      "last_rank": 44,
      "last_seen_ms": 1782165624086,
      "new_entrant_announced": true,
      "drop_off_announced": true
    },
    "0x7e4e766d0ae5ea9cded0c694669194db92800107": {
      "address": "0x7e4e766d0ae5ea9cded0c694669194db92800107",
      "first_seen_in_top_ms": 1780174386009,
      "runs_in_top": 16,
      "consecutive_in_top": 0,
      "last_rank": 44,
      "last_seen_ms": 1782250889465,
      "new_entrant_announced": true,
      "drop_off_announced": true
    },
    "0x6555e1cc97d3cba6eaddebbcd7ca51d75771e0b8": {
      "address": "0x6555e1cc97d3cba6eaddebbcd7ca51d75771e0b8",
      "first_seen_in_top_ms": 1780234797376,
      "runs_in_top": 113,
      "consecutive_in_top": 0,
      "last_rank": 47,
      "last_seen_ms": 1782495883046,
      "new_entrant_announced": true,
      "drop_off_announced": true
    },
    "0x8607a7d180de23645db594d90621d837749408d5": {
      "address": "0x8607a7d180de23645db594d90621d837749408d5",
      "first_seen_in_top_ms": 1780234797376,
      "runs_in_top": 18,
      "consecutive_in_top": 0,
      "last_rank": 43,
      "last_seen_ms": 1783459252771,
      "new_entrant_announced": true,
      "drop_off_announced": true
    },
    "0x97f8219e401f07752a60ddb0a75efda96d1389d9": {
      "address": "0x97f8219e401f07752a60ddb0a75efda96d1389d9",
      "first_seen_in_top_ms": 1780246992000,
      "runs_in_top": 19,
      "consecutive_in_top": 0,
      "last_rank": 34,
      "last_seen_ms": 1781028082661,
      "new_entrant_announced": true,
      "drop_off_announced": true
    },
    "0x156115e100141e9330620c253225cc5ee598a31a": {
      "address": "0x156115e100141e9330620c253225cc5ee598a31a",
      "first_seen_in_top_ms": 1780285471000,
      "runs_in_top": 128,
      "consecutive_in_top": 0,
      "last_rank": 49,
      "last_seen_ms": 1782654027192,
      "new_entrant_announced": true,
      "drop_off_announced": true
    },
    "0x841b31721e95a229f7967578e351ee1dc4ac1d63": {
      "address": "0x841b31721e95a229f7967578e351ee1dc4ac1d63",
      "first_seen_in_top_ms": 1780335207885,
      "runs_in_top": 89,
      "consecutive_in_top": 0,
      "last_rank": 47,
      "last_seen_ms": 1781903268559,
      "new_entrant_announced": true,
      "drop_off_announced": true
    },
    "0xfce053a5e461683454bf37ad66d20344c0e3f4c0": {
      "address": "0xfce053a5e461683454bf37ad66d20344c0e3f4c0",
      "first_seen_in_top_ms": 1780417122230,
      "runs_in_top": 149,
      "consecutive_in_top": 0,
      "last_rank": 47,
      "last_seen_ms": 1782941135511,
      "new_entrant_announced": true,
      "drop_off_announced": true
    },
    "0xb190075e8027cc2df5d3b7749e4548fa8e56fa18": {
      "address": "0xb190075e8027cc2df5d3b7749e4548fa8e56fa18",
      "first_seen_in_top_ms": 1780458571502,
      "runs_in_top": 134,
      "consecutive_in_top": 0,
      "last_rank": 37,
      "last_seen_ms": 1782680322853,
      "new_entrant_announced": true,
      "drop_off_announced": true
    },
    "0xfc667adba8d4837586078f4fdcdc29804337ca06": {
      "address": "0xfc667adba8d4837586078f4fdcdc29804337ca06",
      "first_seen_in_top_ms": 1780504995506,
      "runs_in_top": 197,
      "consecutive_in_top": 197,
      "last_rank": 1,
      "last_seen_ms": 1783632061308,
      "new_entrant_announced": true,
      "drop_off_announced": false
    },
    "0x64264011965176dcb56fd5ca0dd23e3c8a0bfe13": {
      "address": "0x64264011965176dcb56fd5ca0dd23e3c8a0bfe13",
      "first_seen_in_top_ms": 1780561124351,
      "runs_in_top": 71,
      "consecutive_in_top": 0,
      "last_rank": 49,
      "last_seen_ms": 1781870631185,
      "new_entrant_announced": true,
      "drop_off_announced": true
    },
    "0xd4d99d205e67e88e5e19d91afd6fcab665b532e8": {
      "address": "0xd4d99d205e67e88e5e19d91afd6fcab665b532e8",
      "first_seen_in_top_ms": 1780630236966,
      "runs_in_top": 61,
      "consecutive_in_top": 0,
      "last_rank": 37,
      "last_seen_ms": 1782165624086,
      "new_entrant_announced": true,
      "drop_off_announced": true
    },
    "0xbcd420d13362532756c968f663f96ba95e240dd2": {
      "address": "0xbcd420d13362532756c968f663f96ba95e240dd2",
      "first_seen_in_top_ms": 1780630236966,
      "runs_in_top": 128,
      "consecutive_in_top": 0,
      "last_rank": 41,
      "last_seen_ms": 1783112508380,
      "new_entrant_announced": true,
      "drop_off_announced": true
    },
    "0x6859da14835424957a1e6b397d8026b1d9ff7e1e": {
      "address": "0x6859da14835424957a1e6b397d8026b1d9ff7e1e",
      "first_seen_in_top_ms": 1780630236966,
      "runs_in_top": 127,
      "consecutive_in_top": 0,
      "last_rank": 21,
      "last_seen_ms": 1783026125322,
      "new_entrant_announced": true,
      "drop_off_announced": true
    },
    "0xf704ebc79aee732265c7c986fea50a9c01ab7f8d": {
      "address": "0xf704ebc79aee732265c7c986fea50a9c01ab7f8d",
      "first_seen_in_top_ms": 1780630236966,
      "runs_in_top": 5,
      "consecutive_in_top": 0,
      "last_rank": 49,
      "last_seen_ms": 1780694598083,
      "new_entrant_announced": true,
      "drop_off_announced": false
    },
    "0x0a8494f70031623c9c0043aff4d40f334b458b11": {
      "address": "0x0a8494f70031623c9c0043aff4d40f334b458b11",
      "first_seen_in_top_ms": 1780646663113,
      "runs_in_top": 65,
      "consecutive_in_top": 0,
      "last_rank": 31,
      "last_seen_ms": 1783112508380,
      "new_entrant_announced": true,
      "drop_off_announced": true
    },
    "0x42b6d907f36255d48f70db8b4a2684088a162634": {
      "address": "0x42b6d907f36255d48f70db8b4a2684088a162634",
      "first_seen_in_top_ms": 1780646663113,
      "runs_in_top": 1,
      "consecutive_in_top": 0,
      "last_rank": 43,
      "last_seen_ms": 1780646663113,
      "new_entrant_announced": false,
      "drop_off_announced": false
    },
    "0xc59498175d6d317642aeb97f895a7ce1aa992191": {
      "address": "0xc59498175d6d317642aeb97f895a7ce1aa992191",
      "first_seen_in_top_ms": 1780646663113,
      "runs_in_top": 2,
      "consecutive_in_top": 0,
      "last_rank": 47,
      "last_seen_ms": 1780670692660,
      "new_entrant_announced": false,
      "drop_off_announced": false
    },
    "0x856c35038594767646266bc7fd68dc26480e910d": {
      "address": "0x856c35038594767646266bc7fd68dc26480e910d",
      "first_seen_in_top_ms": 1780714330749,
      "runs_in_top": 87,
      "consecutive_in_top": 0,
      "last_rank": 32,
      "last_seen_ms": 1783026125322,
      "new_entrant_announced": true,
      "drop_off_announced": true
    },
    "0x6df99d59cdada18ade521e05edd5e6a2ec91b734": {
      "address": "0x6df99d59cdada18ade521e05edd5e6a2ec91b734",
      "first_seen_in_top_ms": 1780752379464,
      "runs_in_top": 139,
      "consecutive_in_top": 0,
      "last_rank": 47,
      "last_seen_ms": 1783112508380,
      "new_entrant_announced": true,
      "drop_off_announced": true
    },
    "0xd4c1f7e8d876c4749228d515473d36f919583d1d": {
      "address": "0xd4c1f7e8d876c4749228d515473d36f919583d1d",
      "first_seen_in_top_ms": 1780765813238,
      "runs_in_top": 56,
      "consecutive_in_top": 0,
      "last_rank": 38,
      "last_seen_ms": 1783026125322,
      "new_entrant_announced": true,
      "drop_off_announced": true
    },
    "0x091159a8106b077c13e89bc09701117e8b5f129a": {
      "address": "0x091159a8106b077c13e89bc09701117e8b5f129a",
      "first_seen_in_top_ms": 1780827998670,
      "runs_in_top": 153,
      "consecutive_in_top": 0,
      "last_rank": 47,
      "last_seen_ms": 1783491930461,
      "new_entrant_announced": true,
      "drop_off_announced": true
    },
    "0x7dacca323e44f168494c779bb5e7483c468ef410": {
      "address": "0x7dacca323e44f168494c779bb5e7483c468ef410",
      "first_seen_in_top_ms": 1780890140222,
      "runs_in_top": 100,
      "consecutive_in_top": 29,
      "last_rank": 41,
      "last_seen_ms": 1783632061308,
      "new_entrant_announced": true,
      "drop_off_announced": false
    },
    "0x577ae91c7b74f04ddb3a5b399ded8318e9895fd2": {
      "address": "0x577ae91c7b74f04ddb3a5b399ded8318e9895fd2",
      "first_seen_in_top_ms": 1780890140222,
      "runs_in_top": 13,
      "consecutive_in_top": 0,
      "last_rank": 16,
      "last_seen_ms": 1781078697295,
      "new_entrant_announced": true,
      "drop_off_announced": true
    },
    "0xbf49647d017805fcc576ac10f33a788e636f4258": {
      "address": "0xbf49647d017805fcc576ac10f33a788e636f4258",
      "first_seen_in_top_ms": 1781016280352,
      "runs_in_top": 57,
      "consecutive_in_top": 0,
      "last_rank": 16,
      "last_seen_ms": 1781990095740,
      "new_entrant_announced": true,
      "drop_off_announced": true
    },
    "0x936cf4fb95c30ce83f658b5bbb247e4bb381bb0f": {
      "address": "0x936cf4fb95c30ce83f658b5bbb247e4bb381bb0f",
      "first_seen_in_top_ms": 1781028082661,
      "runs_in_top": 156,
      "consecutive_in_top": 12,
      "last_rank": 13,
      "last_seen_ms": 1783632061308,
      "new_entrant_announced": true,
      "drop_off_announced": false
    },
    "0xd8c5228c515db3043dfa0c8cd6f22450ee9a99b0": {
      "address": "0xd8c5228c515db3043dfa0c8cd6f22450ee9a99b0",
      "first_seen_in_top_ms": 1781252612564,
      "runs_in_top": 109,
      "consecutive_in_top": 99,
      "last_rank": 21,
      "last_seen_ms": 1783632061308,
      "new_entrant_announced": true,
      "drop_off_announced": false
    },
    "0xb69fbfd47bcc51c2deb0587bd88f52e1c40238e5": {
      "address": "0xb69fbfd47bcc51c2deb0587bd88f52e1c40238e5",
      "first_seen_in_top_ms": 1781519347192,
      "runs_in_top": 74,
      "consecutive_in_top": 23,
      "last_rank": 32,
      "last_seen_ms": 1783632061308,
      "new_entrant_announced": true,
      "drop_off_announced": false
    },
    "0xd14d535a383b065cf2228963a984d0e2477bee1f": {
      "address": "0xd14d535a383b065cf2228963a984d0e2477bee1f",
      "first_seen_in_top_ms": 1781519347192,
      "runs_in_top": 22,
      "consecutive_in_top": 0,
      "last_rank": 45,
      "last_seen_ms": 1782147050537,
      "new_entrant_announced": true,
      "drop_off_announced": true
    },
    "0x39283a71d1db449d56f8363097adaea5e554e713": {
      "address": "0x39283a71d1db449d56f8363097adaea5e554e713",
      "first_seen_in_top_ms": 1781543477876,
      "runs_in_top": 3,
      "consecutive_in_top": 0,
      "last_rank": 49,
      "last_seen_ms": 1781581647891,
      "new_entrant_announced": true,
      "drop_off_announced": false
    },
    "0xc6758a779bccee1ef0190dbe8292fdf44076795d": {
      "address": "0xc6758a779bccee1ef0190dbe8292fdf44076795d",
      "first_seen_in_top_ms": 1781668280371,
      "runs_in_top": 92,
      "consecutive_in_top": 0,
      "last_rank": 44,
      "last_seen_ms": 1783112508380,
      "new_entrant_announced": true,
      "drop_off_announced": true
    },
    "0x4e23288cee4960f9f962195c22948e4bc7ae20c3": {
      "address": "0x4e23288cee4960f9f962195c22948e4bc7ae20c3",
      "first_seen_in_top_ms": 1781733552728,
      "runs_in_top": 27,
      "consecutive_in_top": 0,
      "last_rank": 8,
      "last_seen_ms": 1783026125322,
      "new_entrant_announced": true,
      "drop_off_announced": true
    },
    "0xfc1ccff3fa575ce4297ac24aa00c06946bcf40da": {
      "address": "0xfc1ccff3fa575ce4297ac24aa00c06946bcf40da",
      "first_seen_in_top_ms": 1781753933597,
      "runs_in_top": 38,
      "consecutive_in_top": 0,
      "last_rank": 45,
      "last_seen_ms": 1782593978323,
      "new_entrant_announced": true,
      "drop_off_announced": true
    },
    "0xa9b95f2a2e7ef219021efc5c04c32761b8553bbd": {
      "address": "0xa9b95f2a2e7ef219021efc5c04c32761b8553bbd",
      "first_seen_in_top_ms": 1781925894868,
      "runs_in_top": 86,
      "consecutive_in_top": 29,
      "last_rank": 12,
      "last_seen_ms": 1783632061308,
      "new_entrant_announced": true,
      "drop_off_announced": false
    },
    "0x632b0a6bb6b6184b97f61a6c773077cab99d1838": {
      "address": "0x632b0a6bb6b6184b97f61a6c773077cab99d1838",
      "first_seen_in_top_ms": 1781925894868,
      "runs_in_top": 10,
      "consecutive_in_top": 0,
      "last_rank": 38,
      "last_seen_ms": 1782165624086,
      "new_entrant_announced": true,
      "drop_off_announced": true
    },
    "0xd21d931890d27b6e7e2e668f27931e17698e90f1": {
      "address": "0xd21d931890d27b6e7e2e668f27931e17698e90f1",
      "first_seen_in_top_ms": 1781941676909,
      "runs_in_top": 13,
      "consecutive_in_top": 4,
      "last_rank": 31,
      "last_seen_ms": 1783632061308,
      "new_entrant_announced": true,
      "drop_off_announced": false
    },
    "0xf605cd3adabbc3110bc3efb85ebe7be57590a527": {
      "address": "0xf605cd3adabbc3110bc3efb85ebe7be57590a527",
      "first_seen_in_top_ms": 1782014070921,
      "runs_in_top": 8,
      "consecutive_in_top": 0,
      "last_rank": 43,
      "last_seen_ms": 1782225750690,
      "new_entrant_announced": true,
      "drop_off_announced": false
    },
    "0x71dfc07de32c2ebf1c4801f4b1c9e40b76d4a23d": {
      "address": "0x71dfc07de32c2ebf1c4801f4b1c9e40b76d4a23d",
      "first_seen_in_top_ms": 1782014070921,
      "runs_in_top": 63,
      "consecutive_in_top": 0,
      "last_rank": 47,
      "last_seen_ms": 1783184468196,
      "new_entrant_announced": true,
      "drop_off_announced": true
    },
    "0xdeb0b9c1e1b234981c4731ea927c464449c1ade2": {
      "address": "0xdeb0b9c1e1b234981c4731ea927c464449c1ade2",
      "first_seen_in_top_ms": 1782030485443,
      "runs_in_top": 5,
      "consecutive_in_top": 0,
      "last_rank": 50,
      "last_seen_ms": 1782165624086,
      "new_entrant_announced": true,
      "drop_off_announced": false
    },
    "0x484bc1608211d0604bf70bae72792a56884562f8": {
      "address": "0x484bc1608211d0604bf70bae72792a56884562f8",
      "first_seen_in_top_ms": 1782147050537,
      "runs_in_top": 76,
      "consecutive_in_top": 43,
      "last_rank": 11,
      "last_seen_ms": 1783632061308,
      "new_entrant_announced": true,
      "drop_off_announced": false
    },
    "0xae6446c95cc4e455e9cf56f28757ab728d88e81e": {
      "address": "0xae6446c95cc4e455e9cf56f28757ab728d88e81e",
      "first_seen_in_top_ms": 1782183330999,
      "runs_in_top": 65,
      "consecutive_in_top": 0,
      "last_rank": 47,
      "last_seen_ms": 1783171099667,
      "new_entrant_announced": true,
      "drop_off_announced": true
    },
    "0x3dc908374e11623d8eb9f07dfc7a2e5e803a54b0": {
      "address": "0x3dc908374e11623d8eb9f07dfc7a2e5e803a54b0",
      "first_seen_in_top_ms": 1782183330999,
      "runs_in_top": 62,
      "consecutive_in_top": 1,
      "last_rank": 43,
      "last_seen_ms": 1783632061308,
      "new_entrant_announced": true,
      "drop_off_announced": false
    },
    "0x6bb971430554e3af58fbd469bce46ab2359a2d23": {
      "address": "0x6bb971430554e3af58fbd469bce46ab2359a2d23",
      "first_seen_in_top_ms": 1782183330999,
      "runs_in_top": 63,
      "consecutive_in_top": 23,
      "last_rank": 29,
      "last_seen_ms": 1783632061308,
      "new_entrant_announced": true,
      "drop_off_announced": false
    },
    "0x49e96e255ba418d08e66c35b588e2f2f3766e1d0": {
      "address": "0x49e96e255ba418d08e66c35b588e2f2f3766e1d0",
      "first_seen_in_top_ms": 1782200661594,
      "runs_in_top": 61,
      "consecutive_in_top": 43,
      "last_rank": 28,
      "last_seen_ms": 1783632061308,
      "new_entrant_announced": true,
      "drop_off_announced": false
    },
    "0x4f7634c03ec4e87e14725c84913ade523c6fad5a": {
      "address": "0x4f7634c03ec4e87e14725c84913ade523c6fad5a",
      "first_seen_in_top_ms": 1782213209836,
      "runs_in_top": 52,
      "consecutive_in_top": 0,
      "last_rank": 38,
      "last_seen_ms": 1783198415220,
      "new_entrant_announced": true,
      "drop_off_announced": true
    },
    "0x123dbca6a27005a3c4ce10cb66ee8ece8fc13bff": {
      "address": "0x123dbca6a27005a3c4ce10cb66ee8ece8fc13bff",
      "first_seen_in_top_ms": 1782213209836,
      "runs_in_top": 63,
      "consecutive_in_top": 0,
      "last_rank": 30,
      "last_seen_ms": 1783284992192,
      "new_entrant_announced": true,
      "drop_off_announced": true
    },
    "0x350e33a777d510616fbdb483d1de3b50d1edfcfb": {
      "address": "0x350e33a777d510616fbdb483d1de3b50d1edfcfb",
      "first_seen_in_top_ms": 1782269778210,
      "runs_in_top": 60,
      "consecutive_in_top": 0,
      "last_rank": 43,
      "last_seen_ms": 1783198415220,
      "new_entrant_announced": true,
      "drop_off_announced": true
    },
    "0xa31441e058492bc7cfffda9aa7623c407ae83a81": {
      "address": "0xa31441e058492bc7cfffda9aa7623c407ae83a81",
      "first_seen_in_top_ms": 1782286660307,
      "runs_in_top": 63,
      "consecutive_in_top": 50,
      "last_rank": 4,
      "last_seen_ms": 1783632061308,
      "new_entrant_announced": true,
      "drop_off_announced": false
    },
    "0xc30c7ea910a71ce06ae840868b0c7e47616ba4c9": {
      "address": "0xc30c7ea910a71ce06ae840868b0c7e47616ba4c9",
      "first_seen_in_top_ms": 1782311285871,
      "runs_in_top": 30,
      "consecutive_in_top": 0,
      "last_rank": 48,
      "last_seen_ms": 1782893354225,
      "new_entrant_announced": true,
      "drop_off_announced": true
    },
    "0x06cecfbac34101ae41c88ebc2450f8602b3d164b": {
      "address": "0x06cecfbac34101ae41c88ebc2450f8602b3d164b",
      "first_seen_in_top_ms": 1782323507500,
      "runs_in_top": 16,
      "consecutive_in_top": 0,
      "last_rank": 39,
      "last_seen_ms": 1783026125322,
      "new_entrant_announced": true,
      "drop_off_announced": true
    },
    "0x418aa6bf98a2b2bc93779f810330d88cde488888": {
      "address": "0x418aa6bf98a2b2bc93779f810330d88cde488888",
      "first_seen_in_top_ms": 1782323507500,
      "runs_in_top": 35,
      "consecutive_in_top": 0,
      "last_rank": 48,
      "last_seen_ms": 1782988500517,
      "new_entrant_announced": true,
      "drop_off_announced": true
    },
    "0xad227f63d34e7251c1d0ab65e64eeea07aee4e44": {
      "address": "0xad227f63d34e7251c1d0ab65e64eeea07aee4e44",
      "first_seen_in_top_ms": 1782336027612,
      "runs_in_top": 33,
      "consecutive_in_top": 6,
      "last_rank": 17,
      "last_seen_ms": 1783632061308,
      "new_entrant_announced": true,
      "drop_off_announced": false
    },
    "0x5647249079e257329ecb6f46ed41821d3c69e7de": {
      "address": "0x5647249079e257329ecb6f46ed41821d3c69e7de",
      "first_seen_in_top_ms": 1782410854582,
      "runs_in_top": 7,
      "consecutive_in_top": 0,
      "last_rank": 40,
      "last_seen_ms": 1783198415220,
      "new_entrant_announced": true,
      "drop_off_announced": false
    },
    "0xca4903c207a0df58bf37d4bc8bbc5210726f53c8": {
      "address": "0xca4903c207a0df58bf37d4bc8bbc5210726f53c8",
      "first_seen_in_top_ms": 1782579975721,
      "runs_in_top": 23,
      "consecutive_in_top": 0,
      "last_rank": 48,
      "last_seen_ms": 1782941135511,
      "new_entrant_announced": true,
      "drop_off_announced": true
    },
    "0xc7290b4b308431a985fa9e3e8a335c2f7650517c": {
      "address": "0xc7290b4b308431a985fa9e3e8a335c2f7650517c",
      "first_seen_in_top_ms": 1782723377014,
      "runs_in_top": 8,
      "consecutive_in_top": 0,
      "last_rank": 45,
      "last_seen_ms": 1783026125322,
      "new_entrant_announced": true,
      "drop_off_announced": false
    },
    "0xd487e26c62ed8c28ce3cc70b5791e501c2934982": {
      "address": "0xd487e26c62ed8c28ce3cc70b5791e501c2934982",
      "first_seen_in_top_ms": 1782723377014,
      "runs_in_top": 2,
      "consecutive_in_top": 0,
      "last_rank": 50,
      "last_seen_ms": 1783046477034,
      "new_entrant_announced": false,
      "drop_off_announced": false
    },
    "0xfe7ce058edc7cfcde9ef8262ba51f8d4796ab7ae": {
      "address": "0xfe7ce058edc7cfcde9ef8262ba51f8d4796ab7ae",
      "first_seen_in_top_ms": 1782768214715,
      "runs_in_top": 24,
      "consecutive_in_top": 11,
      "last_rank": 23,
      "last_seen_ms": 1783632061308,
      "new_entrant_announced": true,
      "drop_off_announced": false
    },
    "0x0c349d9b92fbd172bbb5a17a9db0a673a6a10ad3": {
      "address": "0x0c349d9b92fbd172bbb5a17a9db0a673a6a10ad3",
      "first_seen_in_top_ms": 1782828761413,
      "runs_in_top": 20,
      "consecutive_in_top": 0,
      "last_rank": 50,
      "last_seen_ms": 1783619573230,
      "new_entrant_announced": true,
      "drop_off_announced": true
    },
    "0x50b309f78e774a756a2230e1769729094cac9f20": {
      "address": "0x50b309f78e774a756a2230e1769729094cac9f20",
      "first_seen_in_top_ms": 1782876769244,
      "runs_in_top": 1,
      "consecutive_in_top": 0,
      "last_rank": 39,
      "last_seen_ms": 1782876769244,
      "new_entrant_announced": false,
      "drop_off_announced": false
    },
    "0xf02d16a272a842f8bac1d9a9e773aba1933454c6": {
      "address": "0xf02d16a272a842f8bac1d9a9e773aba1933454c6",
      "first_seen_in_top_ms": 1782893354225,
      "runs_in_top": 18,
      "consecutive_in_top": 0,
      "last_rank": 47,
      "last_seen_ms": 1783608712580,
      "new_entrant_announced": true,
      "drop_off_announced": true
    },
    "0x4a96036fb1529561fa3eeeb2781fad2d4f25500e": {
      "address": "0x4a96036fb1529561fa3eeeb2781fad2d4f25500e",
      "first_seen_in_top_ms": 1782961042873,
      "runs_in_top": 2,
      "consecutive_in_top": 0,
      "last_rank": 50,
      "last_seen_ms": 1782977306801,
      "new_entrant_announced": false,
      "drop_off_announced": false
    },
    "0xf822fa0fd364c573fcdb7009fcf47601bc8be01a": {
      "address": "0xf822fa0fd364c573fcdb7009fcf47601bc8be01a",
      "first_seen_in_top_ms": 1783046477034,
      "runs_in_top": 15,
      "consecutive_in_top": 0,
      "last_rank": 42,
      "last_seen_ms": 1783619573230,
      "new_entrant_announced": true,
      "drop_off_announced": true
    },
    "0xd67ca2c6f8bc84acf4fa4472b82a8740dc0a53ff": {
      "address": "0xd67ca2c6f8bc84acf4fa4472b82a8740dc0a53ff",
      "first_seen_in_top_ms": 1783046477034,
      "runs_in_top": 24,
      "consecutive_in_top": 6,
      "last_rank": 48,
      "last_seen_ms": 1783632061308,
      "new_entrant_announced": true,
      "drop_off_announced": false
    },
    "0x3bcae23e8c380dab4732e9a159c0456f12d866f3": {
      "address": "0x3bcae23e8c380dab4732e9a159c0456f12d866f3",
      "first_seen_in_top_ms": 1783046477034,
      "runs_in_top": 12,
      "consecutive_in_top": 0,
      "last_rank": 49,
      "last_seen_ms": 1783198415220,
      "new_entrant_announced": true,
      "drop_off_announced": true
    },
    "0x1116b5fcc070945062e8879841c29807db373d0d": {
      "address": "0x1116b5fcc070945062e8879841c29807db373d0d",
      "first_seen_in_top_ms": 1783046477034,
      "runs_in_top": 30,
      "consecutive_in_top": 8,
      "last_rank": 37,
      "last_seen_ms": 1783632061308,
      "new_entrant_announced": true,
      "drop_off_announced": false
    },
    "0x5986347c1d0133d02d307f08bb1efd44c2eb89d9": {
      "address": "0x5986347c1d0133d02d307f08bb1efd44c2eb89d9",
      "first_seen_in_top_ms": 1783063076142,
      "runs_in_top": 7,
      "consecutive_in_top": 0,
      "last_rank": 49,
      "last_seen_ms": 1783271163415,
      "new_entrant_announced": true,
      "drop_off_announced": false
    },
    "0xcf5343ba750a6e30afbb1dadda08bc78f8c8ee11": {
      "address": "0xcf5343ba750a6e30afbb1dadda08bc78f8c8ee11",
      "first_seen_in_top_ms": 1783087001439,
      "runs_in_top": 25,
      "consecutive_in_top": 11,
      "last_rank": 36,
      "last_seen_ms": 1783632061308,
      "new_entrant_announced": true,
      "drop_off_announced": false
    },
    "0x15b325660a1c4a9582a7d834c31119c0cb9e3a42": {
      "address": "0x15b325660a1c4a9582a7d834c31119c0cb9e3a42",
      "first_seen_in_top_ms": 1783112508380,
      "runs_in_top": 21,
      "consecutive_in_top": 0,
      "last_rank": 34,
      "last_seen_ms": 1783459252771,
      "new_entrant_announced": true,
      "drop_off_announced": true
    },
    "0x023a3d058020fb76cca98f01b3c48c8938a22355": {
      "address": "0x023a3d058020fb76cca98f01b3c48c8938a22355",
      "first_seen_in_top_ms": 1783132636442,
      "runs_in_top": 27,
      "consecutive_in_top": 23,
      "last_rank": 10,
      "last_seen_ms": 1783632061308,
      "new_entrant_announced": true,
      "drop_off_announced": false
    },
    "0x0facac3bd128fe6d799898a059d3634b877c7a0a": {
      "address": "0x0facac3bd128fe6d799898a059d3634b877c7a0a",
      "first_seen_in_top_ms": 1783147492267,
      "runs_in_top": 3,
      "consecutive_in_top": 0,
      "last_rank": 50,
      "last_seen_ms": 1783184468196,
      "new_entrant_announced": false,
      "drop_off_announced": false
    },
    "0x2025137a136bea7446deba681cbfc7cf1970840e": {
      "address": "0x2025137a136bea7446deba681cbfc7cf1970840e",
      "first_seen_in_top_ms": 1783147492267,
      "runs_in_top": 3,
      "consecutive_in_top": 0,
      "last_rank": 50,
      "last_seen_ms": 1783198415220,
      "new_entrant_announced": false,
      "drop_off_announced": false
    },
    "0x051c2e6d49cf82ebc47f08f9b85800f94fc9693c": {
      "address": "0x051c2e6d49cf82ebc47f08f9b85800f94fc9693c",
      "first_seen_in_top_ms": 1783184468196,
      "runs_in_top": 31,
      "consecutive_in_top": 31,
      "last_rank": 27,
      "last_seen_ms": 1783632061308,
      "new_entrant_announced": true,
      "drop_off_announced": false
    },
    "0x9e875bd28ee5001478c16cb0c8329116a3c3e816": {
      "address": "0x9e875bd28ee5001478c16cb0c8329116a3c3e816",
      "first_seen_in_top_ms": 1783219676209,
      "runs_in_top": 29,
      "consecutive_in_top": 29,
      "last_rank": 15,
      "last_seen_ms": 1783632061308,
      "new_entrant_announced": true,
      "drop_off_announced": false
    },
    "0xfdf891f2b214a4c9374d26595ec6d4080262e381": {
      "address": "0xfdf891f2b214a4c9374d26595ec6d4080262e381",
      "first_seen_in_top_ms": 1783219676209,
      "runs_in_top": 16,
      "consecutive_in_top": 0,
      "last_rank": 37,
      "last_seen_ms": 1783459252771,
      "new_entrant_announced": true,
      "drop_off_announced": true
    },
    "0x265eac78fb57495674227c93065d67abe6f97f70": {
      "address": "0x265eac78fb57495674227c93065d67abe6f97f70",
      "first_seen_in_top_ms": 1783219676209,
      "runs_in_top": 22,
      "consecutive_in_top": 5,
      "last_rank": 50,
      "last_seen_ms": 1783632061308,
      "new_entrant_announced": true,
      "drop_off_announced": false
    },
    "0xa6ee1ed1ae80b8352603654b39f5e7b9bedd5078": {
      "address": "0xa6ee1ed1ae80b8352603654b39f5e7b9bedd5078",
      "first_seen_in_top_ms": 1783219676209,
      "runs_in_top": 12,
      "consecutive_in_top": 6,
      "last_rank": 38,
      "last_seen_ms": 1783632061308,
      "new_entrant_announced": true,
      "drop_off_announced": false
    },
    "0x3ee505ba316879d246a8fd2b3d7ee63b51b44fab": {
      "address": "0x3ee505ba316879d246a8fd2b3d7ee63b51b44fab",
      "first_seen_in_top_ms": 1783219676209,
      "runs_in_top": 6,
      "consecutive_in_top": 0,
      "last_rank": 38,
      "last_seen_ms": 1783284992192,
      "new_entrant_announced": true,
      "drop_off_announced": false
    },
    "0x9ffdf919da72213588f7517598394cc5535bce40": {
      "address": "0x9ffdf919da72213588f7517598394cc5535bce40",
      "first_seen_in_top_ms": 1783219676209,
      "runs_in_top": 7,
      "consecutive_in_top": 0,
      "last_rank": 49,
      "last_seen_ms": 1783519015819,
      "new_entrant_announced": true,
      "drop_off_announced": false
    },
    "0xe09726ff25f5001f37b15049f54116cb83d7d0fe": {
      "address": "0xe09726ff25f5001f37b15049f54116cb83d7d0fe",
      "first_seen_in_top_ms": 1783219676209,
      "runs_in_top": 18,
      "consecutive_in_top": 7,
      "last_rank": 33,
      "last_seen_ms": 1783632061308,
      "new_entrant_announced": true,
      "drop_off_announced": false
    },
    "0x0748e296e5a350ec36c8487a1cea406e1b57d4b2": {
      "address": "0x0748e296e5a350ec36c8487a1cea406e1b57d4b2",
      "first_seen_in_top_ms": 1783271163415,
      "runs_in_top": 24,
      "consecutive_in_top": 5,
      "last_rank": 46,
      "last_seen_ms": 1783632061308,
      "new_entrant_announced": true,
      "drop_off_announced": false
    },
    "0x90dbb196cacf24bd212b377a0dd62eaad5e8151b": {
      "address": "0x90dbb196cacf24bd212b377a0dd62eaad5e8151b",
      "first_seen_in_top_ms": 1783306471351,
      "runs_in_top": 10,
      "consecutive_in_top": 0,
      "last_rank": 49,
      "last_seen_ms": 1783459252771,
      "new_entrant_announced": true,
      "drop_off_announced": true
    },
    "0x118030edbbfde018d7ce43c62138fc271f5202d3": {
      "address": "0x118030edbbfde018d7ce43c62138fc271f5202d3",
      "first_seen_in_top_ms": 1783306471351,
      "runs_in_top": 15,
      "consecutive_in_top": 0,
      "last_rank": 47,
      "last_seen_ms": 1783519015819,
      "new_entrant_announced": true,
      "drop_off_announced": true
    },
    "0x4cd80aa0ce4881eb8679eda1f6fbe3d89aec0f7f": {
      "address": "0x4cd80aa0ce4881eb8679eda1f6fbe3d89aec0f7f",
      "first_seen_in_top_ms": 1783306471351,
      "runs_in_top": 12,
      "consecutive_in_top": 5,
      "last_rank": 39,
      "last_seen_ms": 1783632061308,
      "new_entrant_announced": true,
      "drop_off_announced": false
    },
    "0x64a4fbb71858f681f3fa10a42b34180a9a48088d": {
      "address": "0x64a4fbb71858f681f3fa10a42b34180a9a48088d",
      "first_seen_in_top_ms": 1783306471351,
      "runs_in_top": 8,
      "consecutive_in_top": 0,
      "last_rank": 31,
      "last_seen_ms": 1783421536958,
      "new_entrant_announced": true,
      "drop_off_announced": false
    },
    "0x69906b0ed626ca01a4b7c001e5711e5714ccf207": {
      "address": "0x69906b0ed626ca01a4b7c001e5711e5714ccf207",
      "first_seen_in_top_ms": 1783306471351,
      "runs_in_top": 8,
      "consecutive_in_top": 0,
      "last_rank": 50,
      "last_seen_ms": 1783459252771,
      "new_entrant_announced": true,
      "drop_off_announced": false
    },
    "0x08c14b32c8a48894e4b933090ebcc9ce33b21135": {
      "address": "0x08c14b32c8a48894e4b933090ebcc9ce33b21135",
      "first_seen_in_top_ms": 1783351524963,
      "runs_in_top": 8,
      "consecutive_in_top": 0,
      "last_rank": 47,
      "last_seen_ms": 1783544638274,
      "new_entrant_announced": true,
      "drop_off_announced": false
    },
    "0x15a4f009bb324a3fb9e36137136b201e3fe0dfdb": {
      "address": "0x15a4f009bb324a3fb9e36137136b201e3fe0dfdb",
      "first_seen_in_top_ms": 1783361344697,
      "runs_in_top": 6,
      "consecutive_in_top": 0,
      "last_rank": 45,
      "last_seen_ms": 1783477594192,
      "new_entrant_announced": true,
      "drop_off_announced": false
    },
    "0x007c20e5c339015c924735cf76cb092bc5d9bacc": {
      "address": "0x007c20e5c339015c924735cf76cb092bc5d9bacc",
      "first_seen_in_top_ms": 1783392529906,
      "runs_in_top": 10,
      "consecutive_in_top": 0,
      "last_rank": 43,
      "last_seen_ms": 1783544638274,
      "new_entrant_announced": true,
      "drop_off_announced": true
    },
    "0x80fb5880f38185661962e475ac1557817dc9faea": {
      "address": "0x80fb5880f38185661962e475ac1557817dc9faea",
      "first_seen_in_top_ms": 1783434378711,
      "runs_in_top": 1,
      "consecutive_in_top": 0,
      "last_rank": 50,
      "last_seen_ms": 1783434378711,
      "new_entrant_announced": false,
      "drop_off_announced": false
    },
    "0xfc27136e42af1732ddc9ce2605ea9bff1b959d9d": {
      "address": "0xfc27136e42af1732ddc9ce2605ea9bff1b959d9d",
      "first_seen_in_top_ms": 1783446988421,
      "runs_in_top": 2,
      "consecutive_in_top": 0,
      "last_rank": 14,
      "last_seen_ms": 1783459252771,
      "new_entrant_announced": false,
      "drop_off_announced": false
    },
    "0xe0ffc829349c88c159462942ad885f12130e7610": {
      "address": "0xe0ffc829349c88c159462942ad885f12130e7610",
      "first_seen_in_top_ms": 1783505608264,
      "runs_in_top": 1,
      "consecutive_in_top": 0,
      "last_rank": 43,
      "last_seen_ms": 1783505608264,
      "new_entrant_announced": false,
      "drop_off_announced": false
    },
    "0xd1dd6d99c5fb5d31ff52eacce5046c7158859e85": {
      "address": "0xd1dd6d99c5fb5d31ff52eacce5046c7158859e85",
      "first_seen_in_top_ms": 1783505608264,
      "runs_in_top": 1,
      "consecutive_in_top": 0,
      "last_rank": 45,
      "last_seen_ms": 1783505608264,
      "new_entrant_announced": false,
      "drop_off_announced": false
    },
    "0xdd9f274410c8c704bdbb599dce6c4fb34be4f50a": {
      "address": "0xdd9f274410c8c704bdbb599dce6c4fb34be4f50a",
      "first_seen_in_top_ms": 1783531559877,
      "runs_in_top": 2,
      "consecutive_in_top": 0,
      "last_rank": 44,
      "last_seen_ms": 1783564860320,
      "new_entrant_announced": false,
      "drop_off_announced": false
    },
    "0x325edd95bb016c36027ce3b9f7595af7094a9564": {
      "address": "0x325edd95bb016c36027ce3b9f7595af7094a9564",
      "first_seen_in_top_ms": 1783564860320,
      "runs_in_top": 6,
      "consecutive_in_top": 6,
      "last_rank": 44,
      "last_seen_ms": 1783632061308,
      "new_entrant_announced": true,
      "drop_off_announced": false
    }
  }
}